datamatrix_lib/__init__.py
datamatrix_lib-0.1.dist-info/METADATA
datamatrix_lib-0.1.dist-info/WHEEL
datamatrix_lib-0.1.dist-info/top_level.txt
datamatrix_lib-0.1.dist-info/RECORD
